Workbook

Sheet Instrucciones
B4: CATÁLOGO DE FARMACIA
B5: Hospital Los Ángeles · plantilla de registro de productos · instructivo IC-FAR-01
B7: Objeto | C7: Completar la hoja «Catálogo» con la totalidad de las existencias de farmacia y devolver el archivo. La importación al sistema la efectúa Olympo; no se requiere carga manual.
B8: Un registro por PRESENTACIÓN | C8: No uno por producto. El acetaminofén de 500 mg adquirido en caja de 100, en caja de 80 y en blíster de 10 constituye TRES registros, con la denominación idéntica en los tres y distinta unidad de envase o contenido. El sistema los agrupa bajo un mismo producto.
B9: Unidad de dispensación y unidad de envase | C9: «Se dispensa en» es la unidad MÍNIMA en que el producto se entrega al paciente —TABLETA, MILILITRO, AMPOLLA—. «Unidad del envase» es la presentación en que lo suministra el proveedor —CAJA, FRASCO, BLÍSTER—. El inventario se lleva siempre en la primera.
B10: El tamaño del envase no integra el nombre | C10: «ACETAMINOFÉN JARABE» es la denominación. Los frascos de 60 ml y de 120 ml son dos presentaciones del MISMO producto. Incorporarlos al nombre divide la existencia en dos registros y ninguno concuerda con el conteo físico.
B11: El costo corresponde al ENVASE COMPLETO | C11: Costo de la caja o del frasco completo, sin ISV, según factura del proveedor. El sistema divide por el contenido y determina el precio de venta conforme al margen establecido. La columna gris «Costo por unidad» muestra esa división y permite verificarla.
B12: Código de barras: opcional | C12: Consignar el del envase cuando resulte legible. De no tenerlo, o si el producto se reenvasa, déjese VACÍO: el sistema genera uno propio y lo imprime en la etiqueta.
B13: Casos no previstos | C13: No debe crearse una categoría ni una unidad nuevas: consígnese OTROS INSUMOS y detállese en «Notas». Se resuelve durante la importación. Un registro con una unidad que el sistema no reconoce no puede cargarse.
B14: Hojas del archivo | C14: «Catálogo» es la hoja de llenado. «Ejemplos» reúne 30 casos de referencia: uno por cada unidad de dispensación y por cada unidad de envase. «Listas» contiene los valores admitidos y no debe borrarse ni modificarse.
B16: Documentación de apoyo | C16: El instructivo IC-FAR-01, que acompaña a este archivo, desarrolla el criterio caso por caso, con la totalidad de las categorías y de las formas de dispensación.

Sheet Catálogo
A1: UN REGISTRO POR CADA PRESENTACIÓN. Columnas ÁMBAR: obligatorias. Columnas GRISES: se calculan solas; no deben modificarse. Columnas BLANCAS: opcionales; preferible vacías antes que supuestas. Un producto con varias presentaciones lleva un registro por cada una, con la denominación idéntica.
A2: Nombre del producto | B2: Tipo | C2: Categoría | D2: Se dispensa en | E2: Unidad del envase | F2: Cuánto trae el envase | G2: Costo del envase, sin ISV (L) | H2: Así va a quedar el nombre | I2: Costo por unidad (L) | J2: Código de barras | K2: Principio activo | L2: Registro sanitario ARSA | M2: Código ATC | N2: ¿Exige receta? | O2: ¿Es controlado? | P2: Notas
A3: ACETAMINOFÉN 500 MG TABLETA | B3: Medicamento | C3: MEDICAMENTOS | D3: TABLETA | E3: CAJA | F3: 100 | G3: 450 | H3: =IF(OR($A3="",$D3="",$E3="",$F3=""),"",IFERROR($A3&" / "&IF(AND($F3=1,$D3=$E3),INDEX(Listas!$I$5:$I$25,MATCH($E3,Listas!$H$5:$H$25,0)),INDEX(Listas!$I$5:$I$25,MATCH($E3,Listas!$H$5:$H$25,0))&" X "&TEXT($F3,"0.####")&" "&INDEX(Listas!$I$5:$I$25,MATCH($D3,Listas!$H$5:$H$25,0))),"⚠ revisar la unidad")) -> ACETAMINOFÉN 500 MG TABLETA / CAJA X 100 TAB | I3: =IF(OR($F3="",$G3="",$F3=0),"",$G3/$F3) -> 4.5 | J3: 7501234567890 | K3: ACETAMINOFÉN | L3: ARSA-12345 | M3: N02BE01 | N3: NO | O3: NO | P3: Caso más frecuente: se adquiere por caja y se dispensa por tableta.
H4: =IF(OR($A4="",$D4="",$E4="",$F4=""),"",IFERROR($A4&" / "&IF(AND($F4=1,$D4=$E4),INDEX(Listas!$I$5:$I$25,MATCH($E4,Listas!$H$5:$H$25,0)),INDEX(Listas!$I$5:$I$25,MATCH($E4,Listas!$H$5:$H$25,0))&" X "&TEXT($F4,"0.####")&" "&INDEX(Listas!$I$5:$I$25,MATCH($D4,Listas!$H$5:$H$25,0))),"⚠ revisar la unidad")) | I4: =IF(OR($F4="",$G4="",$F4=0),"",$G4/$F4)
H5: =IF(OR($A5="",$D5="",$E5="",$F5=""),"",IFERROR($A5&" / "&IF(AND($F5=1,$D5=$E5),INDEX(Listas!$I$5:$I$25,MATCH($E5,Listas!$H$5:$H$25,0)),INDEX(Listas!$I$5:$I$25,MATCH($E5,Listas!$H$5:$H$25,0))&" X "&TEXT($F5,"0.####")&" "&INDEX(Listas!$I$5:$I$25,MATCH($D5,Listas!$H$5:$H$25,0))),"⚠ revisar la unidad")) | I5: =IF(OR($F5="",$G5="",$F5=0),"",$G5/$F5)
H6: =IF(OR($A6="",$D6="",$E6="",$F6=""),"",IFERROR($A6&" / "&IF(AND($F6=1,$D6=$E6),INDEX(Listas!$I$5:$I$25,MATCH($E6,Listas!$H$5:$H$25,0)),INDEX(Listas!$I$5:$I$25,MATCH($E6,Listas!$H$5:$H$25,0))&" X "&TEXT($F6,"0.####")&" "&INDEX(Listas!$I$5:$I$25,MATCH($D6,Listas!$H$5:$H$25,0))),"⚠ revisar la unidad")) | I6: =IF(OR($F6="",$G6="",$F6=0),"",$G6/$F6)
H7: =IF(OR($A7="",$D7="",$E7="",$F7=""),"",IFERROR($A7&" / "&IF(AND($F7=1,$D7=$E7),INDEX(Listas!$I$5:$I$25,MATCH($E7,Listas!$H$5:$H$25,0)),INDEX(Listas!$I$5:$I$25,MATCH($E7,Listas!$H$5:$H$25,0))&" X "&TEXT($F7,"0.####")&" "&INDEX(Listas!$I$5:$I$25,MATCH($D7,Listas!$H$5:$H$25,0))),"⚠ revisar la unidad")) | I7: =IF(OR($F7="",$G7="",$F7=0),"",$G7/$F7)
H8: =IF(OR($A8="",$D8="",$E8="",$F8=""),"",IFERROR($A8&" / "&IF(AND($F8=1,$D8=$E8),INDEX(Listas!$I$5:$I$25,MATCH($E8,Listas!$H$5:$H$25,0)),INDEX(Listas!$I$5:$I$25,MATCH($E8,Listas!$H$5:$H$25,0))&" X "&TEXT($F8,"0.####")&" "&INDEX(Listas!$I$5:$I$25,MATCH($D8,Listas!$H$5:$H$25,0))),"⚠ revisar la unidad")) | I8: =IF(OR($F8="",$G8="",$F8=0),"",$G8/$F8)
H9: =IF(OR($A9="",$D9="",$E9="",$F9=""),"",IFERROR($A9&" / "&IF(AND($F9=1,$D9=$E9),INDEX(Listas!$I$5:$I$25,MATCH($E9,Listas!$H$5:$H$25,0)),INDEX(Listas!$I$5:$I$25,MATCH($E9,Listas!$H$5:$H$25,0))&" X "&TEXT($F9,"0.####")&" "&INDEX(Listas!$I$5:$I$25,MATCH($D9,Listas!$H$5:$H$25,0))),"⚠ revisar la unidad")) | I9: =IF(OR($F9="",$G9="",$F9=0),"",$G9/$F9)
H10: =IF(OR($A10="",$D10="",$E10="",$F10=""),"",IFERROR($A10&" / "&IF(AND($F10=1,$D10=$E10),INDEX(Listas!$I$5:$I$25,MATCH($E10,Listas!$H$5:$H$25,0)),INDEX(Listas!$I$5:$I$25,MATCH($E10,Listas!$H$5:$H$25,0))&" X "&TEXT($F10,"0.####")&" "&INDEX(Listas!$I$5:$I$25,MATCH($D10,Listas!$H$5:$H$25,0))),"⚠ revisar la unidad")) | I10: =IF(OR($F10="",$G10="",$F10=0),"",$G10/$F10)
H11: =IF(OR($A11="",$D11="",$E11="",$F11=""),"",IFERROR($A11&" / "&IF(AND($F11=1,$D11=$E11),INDEX(Listas!$I$5:$I$25,MATCH($E11,Listas!$H$5:$H$25,0)),INDEX(Listas!$I$5:$I$25,MATCH($E11,Listas!$H$5:$H$25,0))&" X "&TEXT($F11,"0.####")&" "&INDEX(Listas!$I$5:$I$25,MATCH($D11,Listas!$H$5:$H$25,0))),"⚠ revisar la unidad")) | I11: =IF(OR($F11="",$G11="",$F11=0),"",$G11/$F11)
H12: =IF(OR($A12="",$D12="",$E12="",$F12=""),"",IFERROR($A12&" / "&IF(AND($F12=1,$D12=$E12),INDEX(Listas!$I$5:$I$25,MATCH($E12,Listas!$H$5:$H$25,0)),INDEX(Listas!$I$5:$I$25,MATCH($E12,Listas!$H$5:$H$25,0))&" X "&TEXT($F12,"0.####")&" "&INDEX(Listas!$I$5:$I$25,MATCH($D12,Listas!$H$5:$H$25,0))),"⚠ revisar la unidad")) | I12: =IF(OR($F12="",$G12="",$F12=0),"",$G12/$F12)
H13: =IF(OR($A13="",$D13="",$E13="",$F13=""),"",IFERROR($A13&" / "&IF(AND($F13=1,$D13=$E13),INDEX(Listas!$I$5:$I$25,MATCH($E13,Listas!$H$5:$H$25,0)),INDEX(Listas!$I$5:$I$25,MATCH($E13,Listas!$H$5:$H$25,0))&" X "&TEXT($F13,"0.####")&" "&INDEX(Listas!$I$5:$I$25,MATCH($D13,Listas!$H$5:$H$25,0))),"⚠ revisar la unidad")) | I13: =IF(OR($F13="",$G13="",$F13=0),"",$G13/$F13)
H14: =IF(OR($A14="",$D14="",$E14="",$F14=""),"",IFERROR($A14&" / "&IF(AND($F14=1,$D14=$E14),INDEX(Listas!$I$5:$I$25,MATCH($E14,Listas!$H$5:$H$25,0)),INDEX(Listas!$I$5:$I$25,MATCH($E14,Listas!$H$5:$H$25,0))&" X "&TEXT($F14,"0.####")&" "&INDEX(Listas!$I$5:$I$25,MATCH($D14,Listas!$H$5:$H$25,0))),"⚠ revisar la unidad")) | I14: =IF(OR($F14="",$G14="",$F14=0),"",$G14/$F14)
H15: =IF(OR($A15="",$D15="",$E15="",$F15=""),"",IFERROR($A15&" / "&IF(AND($F15=1,$D15=$E15),INDEX(Listas!$I$5:$I$25,MATCH($E15,Listas!$H$5:$H$25,0)),INDEX(Listas!$I$5:$I$25,MATCH($E15,Listas!$H$5:$H$25,0))&" X "&TEXT($F15,"0.####")&" "&INDEX(Listas!$I$5:$I$25,MATCH($D15,Listas!$H$5:$H$25,0))),"⚠ revisar la unidad")) | I15: =IF(OR($F15="",$G15="",$F15=0),"",$G15/$F15)
... H402: =IF(OR($A402="",$D402="",$E402="",$F402=""),"",IFERROR($A402&" / "&IF(AND($F402=1,$D402=$E402),INDEX(Listas!$I$5:$I$25,MATCH($E402,Listas!$H$5:$H$25,0)),INDEX(Listas!$I$5:$I$25,MATCH($E402,Listas!$H$5:$H$25,0))&" X "&TEXT($F402,"0.####")&" "&INDEX(Listas!$I$5:$I$25,MATCH($D402,Listas!$H$5:$H$25,0))),"⚠ revisar la unidad")) | I402: =IF(OR($F402="",$G402="",$F402=0),"",$G402/$F402)

Sheet Ejemplos
A1: 30 CASOS DE REFERENCIA: uno por cada unidad de dispensación y por cada unidad de envase que el sistema admite. No se importan; sirven de criterio. Obsérvese en particular «Se dispensa en» frente a «Unidad del envase».
A2: Nombre del producto | B2: Tipo | C2: Categoría | D2: Se dispensa en | E2: Unidad del envase | F2: Cuánto trae el envase | G2: Costo del envase, sin ISV (L) | H2: Así va a quedar el nombre | I2: Costo por unidad (L) | J2: Código de barras | K2: Principio activo | L2: Registro sanitario ARSA | M2: Código ATC | N2: ¿Exige receta? | O2: ¿Es controlado? | P2: Notas
A3: ACETAMINOFÉN 500 MG TABLETA | B3: Medicamento | C3: MEDICAMENTOS | D3: TABLETA | E3: CAJA | F3: 100 | G3: 450 | H3: =IFERROR($A3&" / "&IF(AND($F3=1,$D3=$E3),INDEX(Listas!$I$5:$I$25,MATCH($E3,Listas!$H$5:$H$25,0)),INDEX(Listas!$I$5:$I$25,MATCH($E3,Listas!$H$5:$H$25,0))&" X "&TEXT($F3,"0.####")&" "&INDEX(Listas!$I$5:$I$25,MATCH($D3,Listas!$H$5:$H$25,0))),"") -> ACETAMINOFÉN 500 MG TABLETA / CAJA X 100 TAB | I3: =IF($F3=0,"",$G3/$F3) -> 4.5 | J3: 7501234567890 | K3: ACETAMINOFÉN | L3: ARSA-12345 | M3: N02BE01 | N3: NO | O3: NO | P3: Caso más frecuente: se adquiere por caja y se dispensa por tableta.
A4: ACETAMINOFÉN 500 MG TABLETA | B4: Medicamento | C4: MEDICAMENTOS | D4: TABLETA | E4: CAJA | F4: 80 | G4: 368 | H4: =IFERROR($A4&" / "&IF(AND($F4=1,$D4=$E4),INDEX(Listas!$I$5:$I$25,MATCH($E4,Listas!$H$5:$H$25,0)),INDEX(Listas!$I$5:$I$25,MATCH($E4,Listas!$H$5:$H$25,0))&" X "&TEXT($F4,"0.####")&" "&INDEX(Listas!$I$5:$I$25,MATCH($D4,Listas!$H$5:$H$25,0))),"") -> ACETAMINOFÉN 500 MG TABLETA / CAJA X 80 TAB | I4: =IF($F4=0,"",$G4/$F4) -> 4.6 | K4: ACETAMINOFÉN | L4: ARSA-12345 | M4: N02BE01 | N4: NO | O4: NO | P4: Mismo producto en caja de otro tamaño: denominación idéntica; varía el contenido.
A5: ACETAMINOFÉN 500 MG TABLETA | B5: Medicamento | C5: MEDICAMENTOS | D5: TABLETA | E5: BLÍSTER | F5: 10 | G5: 52 | H5: =IFERROR($A5&" / "&IF(AND($F5=1,$D5=$E5),INDEX(Listas!$I$5:$I$25,MATCH($E5,Listas!$H$5:$H$25,0)),INDEX(Listas!$I$5:$I$25,MATCH($E5,Listas!$H$5:$H$25,0))&" X "&TEXT($F5,"0.####")&" "&INDEX(Listas!$I$5:$I$25,MATCH($D5,Listas!$H$5:$H$25,0))),"") -> ACETAMINOFÉN 500 MG TABLETA / BLISTER X 10 TAB | I5: =IF($F5=0,"",$G5/$F5) -> 5.2 | K5: ACETAMINOFÉN | L5: ARSA-12345 | M5: N02BE01 | N5: NO | O5: NO | P5: El mismo producto en BLÍSTER. Tres registros, un solo producto.
A6: OMEPRAZOL 20 MG CÁPSULA | B6: Medicamento | C6: MEDICAMENTOS | D6: CÁPSULA | E6: CAJA | F6: 30 | G6: 195 | H6: =IFERROR($A6&" / "&IF(AND($F6=1,$D6=$E6),INDEX(Listas!$I$5:$I$25,MATCH($E6,Listas!$H$5:$H$25,0)),INDEX(Listas!$I$5:$I$25,MATCH($E6,Listas!$H$5:$H$25,0))&" X "&TEXT($F6,"0.####")&" "&INDEX(Listas!$I$5:$I$25,MATCH($D6,Listas!$H$5:$H$25,0))),"") -> OMEPRAZOL 20 MG CÁPSULA / CAJA X 30 CAP | I6: =IF($F6=0,"",$G6/$F6) -> 6.5 | K6: OMEPRAZOL | L6: ARSA-15220 | M6: A02BC01 | N6: SÍ | O6: NO | P6: CÁPSULA: mismo criterio que la tableta.
A7: LEVONORGESTREL 0.15 MG / ETINILESTRADIOL 0.03 MG | B7: Medicamento | C7: MEDICAMENTOS | D7: BLÍSTER | E7: CAJA | F7: 3 | G7: 168 | H7: =IFERROR($A7&" / "&IF(AND($F7=1,$D7=$E7),INDEX(Listas!$I$5:$I$25,MATCH($E7,Listas!$H$5:$H$25,0)),INDEX(Listas!$I$5:$I$25,MATCH($E7,Listas!$H$5:$H$25,0))&" X "&TEXT($F7,"0.####")&" "&INDEX(Listas!$I$5:$I$25,MATCH($D7,Listas!$H$5:$H$25,0))),"") -> LEVONORGESTREL 0.15 MG / ETINILESTRADIOL 0.03 MG / CAJA X 3 BLISTER | I7: =IF($F7=0,"",$G7/$F7) -> 56 | K7: LEVONORGESTREL, ETINILESTRADIOL | L7: ARSA-26410 | M7: G03AA07 | N7: SÍ | O7: NO | P7: BLÍSTER como unidad de dispensación: el ciclo se entrega completo, nunca por tableta.
A8: ACETAMINOFÉN JARABE 120 MG/5 ML | B8: Medicamento | C8: MEDICAMENTOS | D8: MILILITRO | E8: FRASCO | F8: 120 | G8: 68 | H8: =IFERROR($A8&" / "&IF(AND($F8=1,$D8=$E8),INDEX(Listas!$I$5:$I$25,MATCH($E8,Listas!$H$5:$H$25,0)),INDEX(Listas!$I$5:$I$25,MATCH($E8,Listas!$H$5:$H$25,0))&" X "&TEXT($F8,"0.####")&" "&INDEX(Listas!$I$5:$I$25,MATCH($D8,Listas!$H$5:$H$25,0))),"") -> ACETAMINOFÉN JARABE 120 MG/5 ML / FRASCO X 120 ML | I8: =IF($F8=0,"",$G8/$F8) -> 0.56666667 | K8: ACETAMINOFÉN | L8: ARSA-12346 | M8: N02BE01 | N8: NO | O8: NO | P8: MILILITRO en envase FRASCO: la dosis se mide en ml.
A9: LIDOCAÍNA 2% SOLUCIÓN INYECTABLE | B9: Medicamento | C9: MEDICAMENTOS | D9: CENTÍMETRO CÚBICO | E9: FRASCO | F9: 50 | G9: 142 | H9: =IFERROR($A9&" / "&IF(AND($F9=1,$D9=$E9),INDEX(Listas!$I$5:$I$25,MATCH($E9,Listas!$H$5:$H$25,0)),INDEX(Listas!$I$5:$I$25,MATCH($E9,Listas!$H$5:$H$25,0))&" X "&TEXT($F9,"0.####")&" "&INDEX(Listas!$I$5:$I$25,MATCH($D9,Listas!$H$5:$H$25,0))),"") -> LIDOCAÍNA 2% SOLUCIÓN INYECTABLE / FRASCO X 50 CC | I9: =IF($F9=0,"",$G9/$F9) -> 2.84 | K9: LIDOCAÍNA | L9: ARSA-18033 | M9: N01BB02 | N9: SÍ | O9: NO | P9: CENTÍMETRO CÚBICO: equivale al mililitro; se usa el que indica la etiqueta.
A10: AGUA ESTÉRIL PARA INYECCIÓN 10 ML | B10: Medicamento | C10: SOLUCIONES Y SUEROS | D10: MILILITRO | E10: AMPOLLA | F10: 10 | G10: 9 | H10: =IFERROR($A10&" / "&IF(AND($F10=1,$D10=$E10),INDEX(Listas!$I$5:$I$25,MATCH($E10,Listas!$H$5:$H$25,0)),INDEX(Listas!$I$5:$I$25,MATCH($E10,Listas!$H$5:$H$25,0))&" X "&TEXT($F10,"0.####")&" "&INDEX(Listas!$I$5:$I$25,MATCH($D10,Listas!$H$5:$H$25,0))),"") -> AGUA ESTÉRIL PARA INYECCIÓN 10 ML / AMP X 10 ML | I10: =IF($F10=0,"",$G10/$F10) -> 0.9 | L10: ARSA-40012 | N10: NO | O10: NO | P10: Envase AMPOLLA adquirida suelta, no por caja.
A11: AGUA OXIGENADA 3% A GRANEL | B11: Insumo o material | C11: OTROS INSUMOS | D11: MILILITRO | E11: LITRO | F11: 1000 | G11: 96 | H11: =IFERROR($A11&" / "&IF(AND($F11=1,$D11=$E11),INDEX(Listas!$I$5:$I$25,MATCH($E11,Listas!$H$5:$H$25,0)),INDEX(Listas!$I$5:$I$25,MATCH($E11,Listas!$H$5:$H$25,0))&" X "&TEXT($F11,"0.####")&" "&INDEX(Listas!$I$5:$I$25,MATCH($D11,Listas!$H$5:$H$25,0))),"") -> AGUA OXIGENADA 3% A GRANEL / L X 1000 ML | I11: =IF($F11=0,"",$G11/$F11) -> 0.096 | N11: NO | O11: NO | P11: Envase LITRO: líquido adquirido a granel y fraccionado por mililitro.
A12: HIPOCLORITO DE SODIO 5% | B12: Insumo o material | C12: OTROS INSUMOS | D12: LITRO | E12: CAJA | F12: 12 | G12: 528 | H12: =IFERROR($A12&" / "&IF(AND($F12=1,$D12=$E12),INDEX(Listas!$I$5:$I$25,MATCH($E12,Listas!$H$5:$H$25,0)),INDEX(Listas!$I$5:$I$25,MATCH($E12,Listas!$H$5:$H$25,0))&" X "&TEXT($F12,"0.####")&" "&INDEX(Listas!$I$5:$I$25,MATCH($D12,Listas!$H$5:$H$25,0))),"") -> HIPOCLORITO DE SODIO 5% / CAJA X 12 L | I12: =IF($F12=0,"",$G12/$F12) -> 44 | N12: NO | O12: NO | P12: LITRO como unidad de dispensación: la caja contiene doce envases de un litro.
A13: DIAZEPAM 10 MG / 2 ML SOLUCIÓN INYECTABLE | B13: Medicamento | C13: MEDICAMENTOS | D13: AMPOLLA | E13: CAJA | F13: 25 | G13: 875 | H13: =IFERROR($A13&" / "&IF(AND($F13=1,$D13=$E13),INDEX(Listas!$I$5:$I$25,MATCH($E13,Listas!$H$5:$H$25,0)),INDEX(Listas!$I$5:$I$25,MATCH($E13,Listas!$H$5:$H$25,0))&" X "&TEXT($F13,"0.####")&" "&INDEX(Listas!$I$5:$I$25,MATCH($D13,Listas!$H$5:$H$25,0))),"") -> DIAZEPAM 10 MG / 2 ML SOLUCIÓN INYECTABLE / CAJA X 25 AMP | I13: =IF($F13=0,"",$G13/$F13) -> 35 | K13: DIAZEPAM | L13: ARSA-22101 | M13: N05BA01 | N13: SÍ | O13: SÍ | P13: AMPOLLA: se dispensa íntegra. Producto controlado.
A14: CEFTRIAXONA 1 G POLVO PARA INYECCIÓN | B14: Medicamento | C14: MEDICAMENTOS | D14: VIAL | E14: CAJA | F14: 10 | G14: 640 | H14: =IFERROR($A14&" / "&IF(AND($F14=1,$D14=$E14),INDEX(Listas!$I$5:$I$25,MATCH($E14,Listas!$H$5:$H$25,0)),INDEX(Listas!$I$5:$I$25,MATCH($E14,Listas!$H$5:$H$25,0))&" X "&TEXT($F14,"0.####")&" "&INDEX(Listas!$I$5:$I$25,MATCH($D14,Listas!$H$5:$H$25,0))),"") -> CEFTRIAXONA 1 G POLVO PARA INYECCIÓN / CAJA X 10 VIAL | I14: =IF($F14=0,"",$G14/$F14) -> 64 | K14: CEFTRIAXONA | L14: ARSA-33018 | M14: J01DD04 | N14: SÍ | O14: NO | P14: VIAL: se reconstituye y se emplea completo, no se fracciona en ml.
A15: INSULINA NPH 100 UI/ML 10 ML | B15: Medicamento | C15: MEDICAMENTOS | D15: UNIDAD INTERNACIONAL | E15: VIAL | F15: 1000 | G15: 285 | H15: =IFERROR($A15&" / "&IF(AND($F15=1,$D15=$E15),INDEX(Listas!$I$5:$I$25,MATCH($E15,Listas!$H$5:$H$25,0)),INDEX(Listas!$I$5:$I$25,MATCH($E15,Listas!$H$5:$H$25,0))&" X "&TEXT($F15,"0.####")&" "&INDEX(Listas!$I$5:$I$25,MATCH($D15,Listas!$H$5:$H$25,0))),"") -> INSULINA NPH 100 UI/ML 10 ML / VIAL X 1000 UI | I15: =IF($F15=0,"",$G15/$F15) -> 0.285 | K15: INSULINA HUMANA | L15: ARSA-27740 | M15: A10AC01 | N15: SÍ | O15: NO | P15: UNIDAD INTERNACIONAL en envase VIAL suelto: 10 ml a 100 UI/ml son 1000 UI.
A16: SOLUCIÓN SALINA 0.9% 1000 ML | B16: Medicamento | C16: SOLUCIONES Y SUEROS | D16: BOLSA | E16: CAJA | F16: 12 | G16: 396 | H16: =IFERROR($A16&" / "&IF(AND($F16=1,$D16=$E16),INDEX(Listas!$I$5:$I$25,MATCH($E16,Listas!$H$5:$H$25,0)),INDEX(Listas!$I$5:$I$25,MATCH($E16,Listas!$H$5:$H$25,0))&" X "&TEXT($F16,"0.####")&" "&INDEX(Listas!$I$5:$I$25,MATCH($D16,Listas!$H$5:$H$25,0))),"") -> SOLUCIÓN SALINA 0.9% 1000 ML / CAJA X 12 BOLSA | I16: =IF($F16=0,"",$G16/$F16) -> 33 | K16: CLORURO DE SODIO | L16: ARSA-40077 | M16: B05CB01 | N16: NO | O16: NO | P16: BOLSA: se administra completa; la unidad es la bolsa, no los ml.
A17: SALES DE REHIDRATACIÓN ORAL | B17: Medicamento | C17: MEDICAMENTOS | D17: SOBRE | E17: CAJA | F17: 50 | G17: 210 | H17: =IFERROR($A17&" / "&IF(AND($F17=1,$D17=$E17),INDEX(Listas!$I$5:$I$25,MATCH($E17,Listas!$H$5:$H$25,0)),INDEX(Listas!$I$5:$I$25,MATCH($E17,Listas!$H$5:$H$25,0))&" X "&TEXT($F17,"0.####")&" "&INDEX(Listas!$I$5:$I$25,MATCH($D17,Listas!$H$5:$H$25,0))),"") -> SALES DE REHIDRATACIÓN ORAL / CAJA X 50 SOBRE | I17: =IF($F17=0,"",$G17/$F17) -> 4.2 | L17: ARSA-31005 | M17: A07CA | N17: NO | O17: NO | P17: SOBRE como unidad de dispensación.
A18: CARBÓN ACTIVADO POLVO 50 G | B18: Medicamento | C18: MEDICAMENTOS | D18: SOBRE | E18: SOBRE | F18: 1 | G18: 42 | H18: =IFERROR($A18&" / "&IF(AND($F18=1,$D18=$E18),INDEX(Listas!$I$5:$I$25,MATCH($E18,Listas!$H$5:$H$25,0)),INDEX(Listas!$I$5:$I$25,MATCH($E18,Listas!$H$5:$H$25,0))&" X "&TEXT($F18,"0.####")&" "&INDEX(Listas!$I$5:$I$25,MATCH($D18,Listas!$H$5:$H$25,0))),"") -> CARBÓN ACTIVADO POLVO 50 G / SOBRE | I18: =IF($F18=0,"",$G18/$F18) -> 42 | K18: CARBÓN ACTIVADO | M18: A07BA01 | N18: NO | O18: NO | P18: Envase SOBRE adquirido suelto: el envase constituye la unidad.
A19: SULFADIAZINA DE PLATA CREMA 1% | B19: Medicamento | C19: MEDICAMENTOS | D19: GRAMO | E19: FRASCO | F19: 400 | G19: 320 | H19: =IFERROR($A19&" / "&IF(AND($F19=1,$D19=$E19),INDEX(Listas!$I$5:$I$25,MATCH($E19,Listas!$H$5:$H$25,0)),INDEX(Listas!$I$5:$I$25,MATCH($E19,Listas!$H$5:$H$25,0))&" X "&TEXT($F19,"0.####")&" "&INDEX(Listas!$I$5:$I$25,MATCH($D19,Listas!$H$5:$H$25,0))),"") -> SULFADIAZINA DE PLATA CREMA 1% / FRASCO X 400 G | I19: =IF($F19=0,"",$G19/$F19) -> 0.8 | K19: SULFADIAZINA DE PLATA | L19: ARSA-19660 | M19: D06BA01 | N19: SÍ | O19: NO | P19: GRAMO: la crema se dosifica por peso.
A20: PROGESTERONA MICRONIZADA POLVO | B20: Medicamento | C20: MEDICAMENTOS | D20: MILIGRAMO | E20: FRASCO | F20: 25000 | G20: 1850 | H20: =IFERROR($A20&" / "&IF(AND($F20=1,$D20=$E20),INDEX(Listas!$I$5:$I$25,MATCH($E20,Listas!$H$5:$H$25,0)),INDEX(Listas!$I$5:$I$25,MATCH($E20,Listas!$H$5:$H$25,0))&" X "&TEXT($F20,"0.####")&" "&INDEX(Listas!$I$5:$I$25,MATCH($D20,Listas!$H$5:$H$25,0))),"") -> PROGESTERONA MICRONIZADA POLVO / FRASCO X 25000 MG | I20: =IF($F20=0,"",$G20/$F20) -> 0.074 | K20: PROGESTERONA | L20: ARSA-29014 | M20: G03DA04 | N20: SÍ | O20: NO | P20: MILIGRAMO: solo si farmacia prepara fórmulas magistrales y pesa el insumo.
A21: LEVOTIROXINA SÓDICA POLVO | B21: Medicamento | C21: MEDICAMENTOS | D21: MICROGRAMO | E21: FRASCO | F21: 5000000 | G21: 2400 | H21: =IFERROR($A21&" / "&IF(AND($F21=1,$D21=$E21),INDEX(Listas!$I$5:$I$25,MATCH($E21,Listas!$H$5:$H$25,0)),INDEX(Listas!$I$5:$I$25,MATCH($E21,Listas!$H$5:$H$25,0))&" X "&TEXT($F21,"0.####")&" "&INDEX(Listas!$I$5:$I$25,MATCH($D21,Listas!$H$5:$H$25,0))),"") -> LEVOTIROXINA SÓDICA POLVO / FRASCO X 5000000 MCG | I21: =IF($F21=0,"",$G21/$F21) -> 0.00048 | K21: LEVOTIROXINA | L21: ARSA-29018 | M21: H03AA01 | N21: SÍ | O21: NO | P21: MICROGRAMO: mismo caso que el anterior. De uso excepcional.
A22: GASA ESTÉRIL 10 X 10 CM | B22: Insumo o material | C22: MATERIAL DE CURACION | D22: UNIDAD | E22: CAJA | F22: 100 | G22: 285 | H22: =IFERROR($A22&" / "&IF(AND($F22=1,$D22=$E22),INDEX(Listas!$I$5:$I$25,MATCH($E22,Listas!$H$5:$H$25,0)),INDEX(Listas!$I$5:$I$25,MATCH($E22,Listas!$H$5:$H$25,0))&" X "&TEXT($F22,"0.####")&" "&INDEX(Listas!$I$5:$I$25,MATCH($D22,Listas!$H$5:$H$25,0))),"") -> GASA ESTÉRIL 10 X 10 CM / CAJA X 100 UND | I22: =IF($F22=0,"",$G22/$F22) -> 2.85 | N22: NO | O22: NO | P22: UNIDAD: no corresponde principio activo ni código ATC.
A23: SONDA FOLEY N.º 16 | B23: Insumo o material | C23: DESCARTABLES | D23: UNIDAD | E23: UNIDAD | F23: 1 | G23: 48 | H23: =IFERROR($A23&" / "&IF(AND($F23=1,$D23=$E23),INDEX(Listas!$I$5:$I$25,MATCH($E23,Listas!$H$5:$H$25,0)),INDEX(Listas!$I$5:$I$25,MATCH($E23,Listas!$H$5:$H$25,0))&" X "&TEXT($F23,"0.####")&" "&INDEX(Listas!$I$5:$I$25,MATCH($D23,Listas!$H$5:$H$25,0))),"") -> SONDA FOLEY N.º 16 / UND | I23: =IF($F23=0,"",$G23/$F23) -> 48 | N23: NO | O23: NO | P23: Envase UNIDAD: se adquiere de a una, sin empaque colectivo.
A24: VENDA ELÁSTICA 4 PULGADAS | B24: Insumo o material | C24: MATERIAL DE CURACION | D24: UNIDAD | E24: BOLSA | F24: 12 | G24: 156 | H24: =IFERROR($A24&" / "&IF(AND($F24=1,$D24=$E24),INDEX(Listas!$I$5:$I$25,MATCH($E24,Listas!$H$5:$H$25,0)),INDEX(Listas!$I$5:$I$25,MATCH($E24,Listas!$H$5:$H$25,0))&" X "&TEXT($F24,"0.####")&" "&INDEX(Listas!$I$5:$I$25,MATCH($D24,Listas!$H$5:$H$25,0))),"") -> VENDA ELÁSTICA 4 PULGADAS / BOLSA X 12 UND | I24: =IF($F24=0,"",$G24/$F24) -> 13 | N24: NO | O24: NO | P24: Envase BOLSA: contiene doce vendas, cada una es una unidad.
A25: JERINGA DESCARTABLE 5 ML CON AGUJA | B25: Insumo o material | C25: DESCARTABLES | D25: UNIDAD | E25: CAJA | F25: 100 | G25: 320 | H25: =IFERROR($A25&" / "&IF(AND($F25=1,$D25=$E25),INDEX(Listas!$I$5:$I$25,MATCH($E25,Listas!$H$5:$H$25,0)),INDEX(Listas!$I$5:$I$25,MATCH($E25,Listas!$H$5:$H$25,0))&" X "&TEXT($F25,"0.####")&" "&INDEX(Listas!$I$5:$I$25,MATCH($D25,Listas!$H$5:$H$25,0))),"") -> JERINGA DESCARTABLE 5 ML CON AGUJA / CAJA X 100 UND | I25: =IF($F25=0,"",$G25/$F25) -> 3.2 | N25: NO | O25: NO | P25: Descartable: cada jeringa constituye una unidad.
A26: GUANTE DE EXAMEN LÁTEX TALLA M | B26: Insumo o material | C26: DESCARTABLES | D26: PAR | E26: CAJA | F26: 50 | G26: 210 | H26: =IFERROR($A26&" / "&IF(AND($F26=1,$D26=$E26),INDEX(Listas!$I$5:$I$25,MATCH($E26,Listas!$H$5:$H$25,0)),INDEX(Listas!$I$5:$I$25,MATCH($E26,Listas!$H$5:$H$25,0))&" X "&TEXT($F26,"0.####")&" "&INDEX(Listas!$I$5:$I$25,MATCH($D26,Listas!$H$5:$H$25,0))),"") -> GUANTE DE EXAMEN LÁTEX TALLA M / CAJA X 50 PAR | I26: =IF($F26=0,"",$G26/$F26) -> 4.2 | N26: NO | O26: NO | P26: PAR: la caja contiene 50 pares, no 100 guantes.
A27: GUANTE QUIRÚRGICO ESTÉRIL TALLA 7.5 | B27: Insumo o material | C27: DESCARTABLES | D27: PAR | E27: PAR | F27: 1 | G27: 18 | H27: =IFERROR($A27&" / "&IF(AND($F27=1,$D27=$E27),INDEX(Listas!$I$5:$I$25,MATCH($E27,Listas!$H$5:$H$25,0)),INDEX(Listas!$I$5:$I$25,MATCH($E27,Listas!$H$5:$H$25,0))&" X "&TEXT($F27,"0.####")&" "&INDEX(Listas!$I$5:$I$25,MATCH($D27,Listas!$H$5:$H$25,0))),"") -> GUANTE QUIRÚRGICO ESTÉRIL TALLA 7.5 / PAR | I27: =IF($F27=0,"",$G27/$F27) -> 18 | N27: NO | O27: NO | P27: Envase PAR: se adquiere por par estéril individual.
A28: EQUIPO DE VENOCLISIS MACROGOTERO | B28: Insumo o material | C28: DESCARTABLES | D28: KIT | E28: KIT | F28: 1 | G28: 27 | H28: =IFERROR($A28&" / "&IF(AND($F28=1,$D28=$E28),INDEX(Listas!$I$5:$I$25,MATCH($E28,Listas!$H$5:$H$25,0)),INDEX(Listas!$I$5:$I$25,MATCH($E28,Listas!$H$5:$H$25,0))&" X "&TEXT($F28,"0.####")&" "&INDEX(Listas!$I$5:$I$25,MATCH($D28,Listas!$H$5:$H$25,0))),"") -> EQUIPO DE VENOCLISIS MACROGOTERO / KIT | I28: =IF($F28=0,"",$G28/$F28) -> 27 | N28: NO | O28: NO | P28: KIT en envase KIT: conjunto que no se fracciona.
A29: VENDA DE GASA EN ROLLO 10 CM X 5 M | B29: Insumo o material | C29: MATERIAL DE CURACION | D29: CENTÍMETRO | E29: UNIDAD | F29: 500 | G29: 22 | H29: =IFERROR($A29&" / "&IF(AND($F29=1,$D29=$E29),INDEX(Listas!$I$5:$I$25,MATCH($E29,Listas!$H$5:$H$25,0)),INDEX(Listas!$I$5:$I$25,MATCH($E29,Listas!$H$5:$H$25,0))&" X "&TEXT($F29,"0.####")&" "&INDEX(Listas!$I$5:$I$25,MATCH($D29,Listas!$H$5:$H$25,0))),"") -> VENDA DE GASA EN ROLLO 10 CM X 5 M / UND X 500 CM | I29: =IF($F29=0,"",$G29/$F29) -> 0.044 | N29: NO | O29: NO | P29: CENTÍMETRO: el rollo de 5 m equivale a 500 cm y se corta a medida.
A30: TUBULADURA DE SILICONA GRADO MÉDICO | B30: Insumo o material | C30: OTROS INSUMOS | D30: METRO | E30: UNIDAD | F30: 25 | G30: 890 | H30: =IFERROR($A30&" / "&IF(AND($F30=1,$D30=$E30),INDEX(Listas!$I$5:$I$25,MATCH($E30,Listas!$H$5:$H$25,0)),INDEX(Listas!$I$5:$I$25,MATCH($E30,Listas!$H$5:$H$25,0))&" X "&TEXT($F30,"0.####")&" "&INDEX(Listas!$I$5:$I$25,MATCH($D30,Listas!$H$5:$H$25,0))),"") -> TUBULADURA DE SILICONA GRADO MÉDICO / UND X 25 METRO | I30: =IF($F30=0,"",$G30/$F30) -> 35.6 | N30: NO | O30: NO | P30: METRO: el rollo de 25 m se corta según necesidad.
A31: ALCOHOL ETÍLICO 70% 1 LITRO | B31: Insumo o material | C31: OTROS INSUMOS | D31: FRASCO | E31: FRASCO | F31: 1 | G31: 78 | H31: =IFERROR($A31&" / "&IF(AND($F31=1,$D31=$E31),INDEX(Listas!$I$5:$I$25,MATCH($E31,Listas!$H$5:$H$25,0)),INDEX(Listas!$I$5:$I$25,MATCH($E31,Listas!$H$5:$H$25,0))&" X "&TEXT($F31,"0.####")&" "&INDEX(Listas!$I$5:$I$25,MATCH($D31,Listas!$H$5:$H$25,0))),"") -> ALCOHOL ETÍLICO 70% 1 LITRO / FRASCO | I31: =IF($F31=0,"",$G31/$F31) -> 78 | N31: NO | O31: NO | P31: FRASCO en envase FRASCO con contenido 1: la denominación omite el factor.
A32: TIRAS REACTIVAS DE GLUCOMETRÍA X 50 | B32: Insumo o material | C32: DESCARTABLES | D32: CAJA | E32: CAJA | F32: 1 | G32: 480 | H32: =IFERROR($A32&" / "&IF(AND($F32=1,$D32=$E32),INDEX(Listas!$I$5:$I$25,MATCH($E32,Listas!$H$5:$H$25,0)),INDEX(Listas!$I$5:$I$25,MATCH($E32,Listas!$H$5:$H$25,0))&" X "&TEXT($F32,"0.####")&" "&INDEX(Listas!$I$5:$I$25,MATCH($D32,Listas!$H$5:$H$25,0))),"") -> TIRAS REACTIVAS DE GLUCOMETRÍA X 50 / CAJA | I32: =IF($F32=0,"",$G32/$F32) -> 480 | N32: NO | O32: NO | P32: CAJA como unidad de dispensación: excepcional; solo si nunca se abre.

Sheet Listas
A1: VALORES QUE EL SISTEMA ACEPTA
A2: Esta hoja alimenta los desplegables de la hoja «Catálogo». No debe borrarse ni modificarse: un valor que el sistema no reconozca impide importar el registro.
A4: TIPO | B4: Qué entra acá | D4: CATEGORÍA | E4: Código | F4: Qué entra acá | H4: UNIDAD | I4: Código | J4: Mide | K4: Cuándo se usa | M4: SÍ / NO
A5: Medicamento | B5: Productos farmacéuticos que se prescriben: tabletas, jarabes, ampollas, inyectables. | D5: MEDICAMENTOS | E5: MED | F5: Fármacos en cualquier forma farmacéutica. | H5: UNIDAD | I5: UND | J5: Conteo | K5: Lo que se cuenta de a uno y no tiene forma propia. | M5: SÍ
A6: Insumo o material | B6: Material empleado en la atención: gasas, jeringas, sondas, guantes, tubos. | D6: MATERIAL DE CURACION | E6: MTC | F6: Gasas, vendas, apósitos, suturas, antisépticos. | H6: TABLETA | I6: TAB | J6: Conteo | K6: La tableta suelta. | M6: NO
A7: Otro | B7: Lo que no corresponde a las dos categorías anteriores y aun así se almacena y se factura. | D7: DESCARTABLES | E7: DES | F7: Jeringas, guantes, mascarillas, sondas, catéteres. | H7: CÁPSULA | I7: CAP | J7: Conteo | K7: La cápsula suelta.
D8: SOLUCIONES Y SUEROS | E8: SOL | F8: Suero fisiológico, dextrosa, Hartmann, agua estéril. | H8: AMPOLLA | I8: AMP | J8: Conteo | K8: La ampolla de vidrio, entera.
D9: OTROS INSUMOS | E9: INS | F9: Productos que no corresponden a ninguna de las categorías anteriores. | H9: VIAL | I9: VIAL | J9: Conteo | K9: El frasco-ampolla de inyectable.
H10: FRASCO | I10: FRASCO | J10: Conteo | K10: El frasco entero, cuando no se fracciona.
H11: SOBRE | I11: SOBRE | J11: Conteo | K11: El sobre de polvo o granulado.
H12: CAJA | I12: CAJA | J12: Conteo | K12: La caja del proveedor. Casi siempre va como ENVASE, no como dispensación.
H13: BLÍSTER | I13: BLISTER | J13: Conteo | K13: La tira de tabletas o cápsulas.
H14: PAR | I14: PAR | J14: Conteo | K14: Lo que sale de a dos: guantes, medias.
H15: KIT | I15: KIT | J15: Conteo | K15: El set completo que no se abre por partes.
H16: BOLSA | I16: BOLSA | J16: Conteo | K16: La bolsa de solución o de material.
H17: MILILITRO | I17: ML | J17: Volumen | K17: Para líquidos que se dan por dosis: jarabes, gotas, inyectables.
H18: CENTÍMETRO CÚBICO | I18: CC | J18: Volumen | K18: Lo mismo que el mililitro. Usá el que diga la etiqueta.
H19: LITRO | I19: L | J19: Volumen | K19: Para líquidos a granel.
H20: MILIGRAMO | I20: MG | J20: Masa | K20: Para polvos y cremas que se pesan.
H21: GRAMO | I21: G | J21: Masa | K21: Para polvos, cremas y pomadas.
... H25: METRO | I25: METRO | J25: Longitud | K25: Lo mismo, cuando se mide en metros.
